matrix_operations_cuni/__init__.py
matrix_operations_cuni/core.py
matrix_operations_cuni/operations.py
matrix_operations_cuni/transformations.py
matrix_operations_cuni-0.6.3.dist-info/LICENSE.txt
matrix_operations_cuni-0.6.3.dist-info/METADATA
matrix_operations_cuni-0.6.3.dist-info/WHEEL
matrix_operations_cuni-0.6.3.dist-info/top_level.txt
matrix_operations_cuni-0.6.3.dist-info/RECORD
